aside/__init__.py
aside/__main__.py
aside/_version.py
aside/config.py
aside/resources.py
aside/theme.py
aside/version.py
aside/_resources/add.svg.int
aside/_resources/delete.svg.int
aside/_resources/favicon.ico
aside/_resources/icon.svg
aside/_resources/icon.svg.int
aside/_resources/info.svg.int
aside/_resources/logo.svg
aside/_resources/logo.svg.int
aside/_resources/queue.svg.int
aside/_resources/queue_add.svg.int
aside/_resources/queue_closed.svg.int
aside/_resources/settings.svg.int
aside/_resources/style_sheet.qss.int
aside/_resources/task.svg.int
aside/_resources/task_done.svg.int
aside/_resources/task_warn.svg.int
aside/boilerplate/__init__.py
aside/boilerplate/attributes.py
aside/boilerplate/hooks.py
aside/boilerplate/observable.py
aside/boilerplate/timeutils.py
aside/gui/__init__.py
aside/gui/common.py
aside/gui/main_window.py
aside/gui/queue.py
aside/gui/task.py
aside/models/__init__.py
aside/models/database.py
aside/models/models.py
aside-0.1.2.dist-info/LICENSE
aside-0.1.2.dist-info/METADATA
aside-0.1.2.dist-info/WHEEL
aside-0.1.2.dist-info/entry_points.txt
aside-0.1.2.dist-info/top_level.txt
aside-0.1.2.dist-info/RECORD
