Metadata-Version: 2.1
Name: aside
Version: 0.1.2
Summary: Personal task tracker with the organization of tasks in the form of queues.
Home-page: https://gitlab.com/python-aside/aside/
Author: ruro
Author-email: ruro.ruro@ya.ru
License: UNKNOWN
Project-URL: Bug Tracker, https://gitlab.com/python-aside/aside/-/issues/
Project-URL: Source Code, https://gitlab.com/python-aside/aside/
Project-URL: Documentation, https://aside.rtfd.io/
Keywords: task,tracker,todo,gui
Platform: Any
Classifier: Development Status :: 3 - Alpha
Classifier: Environment :: X11 Applications :: Qt
Classifier: License :: OSI Approved :: GNU Affero General Public License v3
Classifier: Operating System :: OS Independent
Classifier: Programming Language :: Python :: 3 :: Only
Classifier: Programming Language :: Python :: 3.6
Classifier: Programming Language :: Python :: 3.7
Classifier: Programming Language :: Python :: 3.8
Classifier: Programming Language :: Python :: 3.9
Requires-Python: >=3.6
License-File: LICENSE
Requires-Dist: PyQt5
Requires-Dist: arrow
Requires-Dist: attrs
Requires-Dist: attrs-strict
Requires-Dist: dateparser
Requires-Dist: setuptools
Requires-Dist: typing-extensions
Requires-Dist: xdg
Requires-Dist: importlib-metadata ; python_version < "3.10"
Requires-Dist: importlib-resources ; python_version < "3.9"
